test_actions/main.py
test_actions-23.9.16.dist-info/METADATA
test_actions-23.9.16.dist-info/WHEEL
test_actions-23.9.16.dist-info/entry_points.txt
test_actions-23.9.16.dist-info/RECORD
